yamux/__init__.py
yamux-0.0.1.dist-info/LICENSE
yamux-0.0.1.dist-info/METADATA
yamux-0.0.1.dist-info/WHEEL
yamux-0.0.1.dist-info/top_level.txt
yamux-0.0.1.dist-info/RECORD
