Metadata-Version: 2.1
Name: yamux
Version: 0.0.1
Summary: yamux implementation written in python
Home-page: https://github.com/mhchia/py-yamux
Author: Kevin Mai-Hsuan Chia
Author-email: kevin@mhchia.com
License: MIT
Platform: UNKNOWN
Classifier: Programming Language :: Python :: 3
Classifier: Programming Language :: Python :: 3.6
Classifier: Programming Language :: Python :: 3.7
Classifier: Programming Language :: Python :: 3.8
Classifier: License :: OSI Approved :: MIT License
Classifier: Operating System :: OS Independent
Provides-Extra: dev
Requires-Dist: codecov (<3.0.0,>=2.0.15) ; extra == 'dev'
Requires-Dist: factory-boy (<3.0.0,>=2.12.0) ; extra == 'dev'
Requires-Dist: pytest (<5.0.0,>=4.6.3) ; extra == 'dev'
Requires-Dist: pytest-cov (<3.0.0,>=2.7.1) ; extra == 'dev'
Requires-Dist: pytest-asyncio (<1.0.0,>=0.10.0) ; extra == 'dev'
Requires-Dist: mypy (<1.0,>=0.701) ; extra == 'dev'
Requires-Dist: black (>=19.3b0) ; extra == 'dev'
Requires-Dist: isort (==4.3.21) ; extra == 'dev'
Requires-Dist: flake8 (<4.0.0,>=3.7.7) ; extra == 'dev'
Requires-Dist: tox (<4.0.0,>=3.13.2) ; extra == 'dev'
Provides-Extra: lint
Requires-Dist: mypy (<1.0,>=0.701) ; extra == 'lint'
Requires-Dist: black (>=19.3b0) ; extra == 'lint'
Requires-Dist: isort (==4.3.21) ; extra == 'lint'
Requires-Dist: flake8 (<4.0.0,>=3.7.7) ; extra == 'lint'
Provides-Extra: test
Requires-Dist: codecov (<3.0.0,>=2.0.15) ; extra == 'test'
Requires-Dist: factory-boy (<3.0.0,>=2.12.0) ; extra == 'test'
Requires-Dist: pytest (<5.0.0,>=4.6.3) ; extra == 'test'
Requires-Dist: pytest-cov (<3.0.0,>=2.7.1) ; extra == 'test'
Requires-Dist: pytest-asyncio (<1.0.0,>=0.10.0) ; extra == 'test'
